xsendfile.py
xsendfile-1.0rc2.dist-info/DESCRIPTION.rst
xsendfile-1.0rc2.dist-info/RECORD
xsendfile-1.0rc2.dist-info/metadata.json
xsendfile-1.0rc2.dist-info/top_level.txt
xsendfile-1.0rc2.dist-info/METADATA
xsendfile-1.0rc2.dist-info/WHEEL
