Metadata-Version: 2.0
Name: xsendfile
Version: 1.0rc2
Summary: X-Sendfile implementation in Python/WSGI
Home-page: http://pythonhosted.org/xsendfile/
Author: 2degrees Limited
Author-email: 2degrees-floss@2degreesnetwork.com
License: BSD (http://dev.2degreesnetwork.com/p/2degrees-license.html)
Keywords: x-sendfile xsendfile x-accel authorization token url hot-link
Platform: UNKNOWN
Classifier: Development Status :: 5 - Production/Stable
Classifier: Environment :: Web Environment
Classifier: Intended Audience :: Developers
Classifier: License :: OSI Approved :: BSD License
Classifier: Natural Language :: English
Classifier: Operating System :: OS Independent
Classifier: Programming Language :: Python :: 2
Classifier: Topic :: Internet :: WWW/HTTP
Classifier: Topic :: Internet :: WWW/HTTP :: WSGI
Classifier: Topic :: Security
Requires-Dist: Paste (>=2.0.2)
Requires-Dist: six (>=1.10)
